{
  "_class": "symbolInstance",
  "do_objectID": "08381BFA-4D89-4708-9EE1-1B739D65B76F",
  "exportOptions": {
    "_class": "exportOptions",
    "exportFormats": [
    ],
    "includedLayerIds": [
    ],
    "layerOptions": 0,
    "shouldTrim": false
  },
  "frame": {
    "_class": "rect",
    "constrainProportions": false,
    "height": 64,
    "width": 1024,
    "x": 0,
    "y": 0
  },
  "horizontalSpacing": 0,
  "isFlippedHorizontal": false,
  "isFlippedVertical": false,
  "isLocked": false,
  "isVisible": true,
  "layerListExpandedType": 0,
  "masterInfluenceEdgeMaxXPadding": 4,
  "masterInfluenceEdgeMaxYPadding": 6,
  "masterInfluenceEdgeMinXPadding": 4,
  "masterInfluenceEdgeMinYPadding": 2,
  "name": "Header",
  "nameIsFixed": false,
  "resizingConstraint": 63,
  "resizingType": 0,
  "rotation": 0,
  "shouldBreakMaskChain": false,
  "style": {
    "_class": "style",
    "endDecorationType": 0,
    "miterLimit": 10,
    "startDecorationType": 0
  },
  "symbolID": "463FB5D4-FFFF-44A5-BCB6-77A8F0C6DDA5",
  "verticalSpacing": 0
}